{
  "title": "Keeper of the Pearl",
  "description": "This is the story of two lovers, Jae Moon and Ji Yeon, fated for each other as a dragon is to its pearl. Their love overcame the barrier of hierarchy, but the star-crossed lovers were torn apart when one of them was killed in a tragic incident.\n\nThe reincarnated Jae Moon and Ji Yeon are reunited once again in the present time. With such a tragedy in their past lives, will the two be able to rekindle the feelings they had for each other from a happier past?\n\nStatus: Completed\n\nTags: Webtoon, Yaoi, Mature, Smut, Historical, Romance",
  "artist": "Dorook",
  "author": "Dorook",
  "cover": "https://github.com/aoba-seragakii/manga/blob/main/Keeper%20of%20the%20Pearl/Keeper_of_the_Pearl.webp?raw=true",
  "chapters": {
    "0": {
      "title": "0",
      "volume": "",
      "last_updated": "1735094626",
      "groups": {
        "": [
          "https://cubarimanga.wordpress.com/wp-content/uploads/2025/02/001.jpeg",
          "https://cubarimanga.wordpress.com/wp-content/uploads/2025/02/002.jpeg",
          "https://cubarimanga.wordpress.com/wp-content/uploads/2025/02/003.jpeg",
          "https://cubarimanga.wordpress.com/wp-content/uploads/2025/02/004.jpeg",
          "https://cubarimanga.wordpress.com/wp-content/uploads/2025/02/005.jpeg",
          "https://cubarimanga.wordpress.com/wp-content/uploads/2025/02/006.jpeg",
          "https://cubarimanga.wordpress.com/wp-content/uploads/2025/02/007.jpeg",
          "https://cubarimanga.wordpress.com/wp-content/uploads/2025/02/008.jpeg",
          "https://cubarimanga.wordpress.com/wp-content/uploads/2025/02/009.jpeg"
        ]
      }
    },
    "1": {
      "title": "1",
      "volume": "",
      "last_updated": "1735094654",
      "groups": {
        "": "/proxy/api/mangadex/chapter/c96bfa49-36a1-422b-9985-08c65547542d"
      }
    },
    "2": {
      "title": "2",
      "volume": "",
      "last_updated": "1735094663",
      "groups": {
        "": "/proxy/api/mangadex/chapter/a2a3376f-81d9-43f8-bcba-e97635984aea"
      }
    },
    "3": {
      "title": "3",
      "volume": "",
      "last_updated": "1735094674",
      "groups": {
        "": "/proxy/api/mangadex/chapter/73b7e861-c35c-4b10-ad0b-822dd61ed4a9"
      }
    },
    "4": {
      "title": "4",
      "volume": "",
      "last_updated": "1735094692",
      "groups": {
        "": "/proxy/api/mangadex/chapter/a0e9b05f-6634-49b2-ad92-c4eb4b59b106"
      }
    },
    "5": {
      "title": "5",
      "volume": "",
      "last_updated": "1735094701",
      "groups": {
        "": "/proxy/api/mangadex/chapter/aa564c43-4bd9-4eae-b719-fbf304c13455"
      }
    },
    "6": {
      "title": "6",
      "volume": "",
      "last_updated": "1735094725",
      "groups": {
        "": "/proxy/api/mangadex/chapter/617a64e4-b890-4e8a-852b-015b2e52e774"
      }
    },
    "7": {
      "title": "7",
      "volume": "",
      "last_updated": "1735094735",
      "groups": {
        "": "/proxy/api/mangadex/chapter/f6f045fb-745b-4619-8530-d27d87de4cfd"
      }
    },
    "8": {
      "title": "8",
      "volume": "",
      "last_updated": "1735094768",
      "groups": {
        "": "/proxy/api/mangadex/chapter/a92e506a-d3d8-4a60-be3f-f7e0bc1904a8"
      }
    },
    "9": {
      "title": "9",
      "volume": "",
      "last_updated": "1735094801",
      "groups": {
        "": "/proxy/api/mangadex/chapter/e730748b-e027-4e07-92ac-c0e91fc937ac"
      }
    },
    "10": {
      "title": "10",
      "volume": "",
      "last_updated": "1735094845",
      "groups": {
        "": "/proxy/api/mangadex/chapter/a2949b68-25b4-4fd3-9575-1eb67a7df42d"
      }
    },
    "11": {
      "title": "11",
      "volume": "",
      "last_updated": "1735094941",
      "groups": {
        "": "/proxy/api/mangadex/chapter/5bd7d363-48bd-46ec-a99d-4193bb3dbf29"
      }
    },
    "12": {
      "title": "12",
      "volume": "",
      "last_updated": "1735094961",
      "groups": {
        "": "/proxy/api/mangadex/chapter/c6807b3f-cb20-4e34-8c2b-f7065c73276c"
      }
    },
    "13": {
      "title": "13",
      "volume": "",
      "last_updated": "1735094989",
      "groups": {
        "": "/proxy/api/mangadex/chapter/7ea847fb-899a-4be3-a051-44e29cfc863e"
      }
    },
    "14": {
      "title": "14",
      "volume": "",
      "last_updated": "1735095008",
      "groups": {
        "": "/proxy/api/mangadex/chapter/b6c7c3e6-5c0d-470f-a2b6-bea62af68897"
      }
    },
    "15": {
      "title": "15",
      "volume": "",
      "last_updated": "1735095047",
      "groups": {
        "": "/proxy/api/mangadex/chapter/2bb9f7b1-9108-4463-9dfe-b0a81b06a495"
      }
    },
    "16": {
      "title": "16",
      "volume": "",
      "last_updated": "1735095078",
      "groups": {
        "": "/proxy/api/mangadex/chapter/305f2057-6f58-47b5-b4c0-763ee7d04365"
      }
    },
    "17": {
      "title": "17",
      "volume": "",
      "last_updated": "1735095121",
      "groups": {
        "": "/proxy/api/mangadex/chapter/b6f1ecae-2186-466d-836a-da8b33a6a81e"
      }
    },
    "18": {
      "title": "18",
      "volume": "",
      "last_updated": "1735095135",
      "groups": {
        "": "/proxy/api/mangadex/chapter/bccfb711-a78e-45c3-8c9d-f03923a65da1"
      }
    },
    "19": {
      "title": "19",
      "volume": "",
      "last_updated": "1735095148",
      "groups": {
        "": "/proxy/api/mangadex/chapter/a14a84ee-a228-4ddd-979c-8871da822939"
      }
    },
    "20": {
      "title": "20",
      "volume": "",
      "last_updated": "1735095162",
      "groups": {
        "": "/proxy/api/mangadex/chapter/1487e06e-3bc6-4e8c-a3b2-e1f6fa68f4df"
      }
    },
    "21": {
      "title": "21",
      "volume": "",
      "last_updated": "1735095177",
      "groups": {
        "": "/proxy/api/mangadex/chapter/6424602d-7dff-41cd-92b0-39f5009a53d8"
      }
    },
    "22": {
      "title": "22",
      "volume": "",
      "last_updated": "1735095190",
      "groups": {
        "": "/proxy/api/mangadex/chapter/f1e2e2e4-464a-44e0-8e9c-bc8fb57fd9be"
      }
    },
    "23": {
      "title": "23",
      "volume": "",
      "last_updated": "1735095203",
      "groups": {
        "": "/proxy/api/mangadex/chapter/4871abf4-ef8f-4bae-af8a-7c4391432787"
      }
    },
    "24": {
      "title": "24",
      "volume": "",
      "last_updated": "1735095217",
      "groups": {
        "": "/proxy/api/mangadex/chapter/39c8e653-bef3-4566-9e66-2a44893bd40d"
      }
    },
    "25": {
      "title": "25",
      "volume": "",
      "last_updated": "1735095231",
      "groups": {
        "": "/proxy/api/mangadex/chapter/c7acea35-b4c4-4439-a17e-0a07b21cdfbe"
      }
    },
    "26": {
      "title": "26",
      "volume": "",
      "last_updated": "1735095245",
      "groups": {
        "": "/proxy/api/mangadex/chapter/a1b197c5-e6bd-4844-b737-10f667478f2a"
      }
    },
    "27": {
      "title": "27",
      "volume": "",
      "last_updated": "1735095261",
      "groups": {
        "": "/proxy/api/mangadex/chapter/cd8a19b6-4199-4cd5-8f57-327433045f67"
      }
    },
    "28": {
      "title": "28",
      "volume": "",
      "last_updated": "1735095274",
      "groups": {
        "": "/proxy/api/mangadex/chapter/2c9e45a8-f26f-4e84-8444-db465f746573"
      }
    },
    "29": {
      "title": "29",
      "volume": "",
      "last_updated": "1735095288",
      "groups": {
        "": "/proxy/api/mangadex/chapter/72f4b650-b06e-4f3a-8c90-cb90a0653bcd"
      }
    },
    "30": {
      "title": "30",
      "volume": "",
      "last_updated": "1735095302",
      "groups": {
        "": "/proxy/api/mangadex/chapter/27312dc7-e077-4903-a19f-8dc5856c0abb"
      }
    },
    "31": {
      "title": "31",
      "volume": "",
      "last_updated": "1735095316",
      "groups": {
        "": "/proxy/api/mangadex/chapter/9b61f8cf-62cf-430a-9459-0564a98ebd40"
      }
    },
    "32": {
      "title": "32",
      "volume": "",
      "last_updated": "1735095330",
      "groups": {
        "": "/proxy/api/mangadex/chapter/926a684f-00a6-4dd2-9266-3ee7aa512e8d"
      }
    },
    "33": {
      "title": "33",
      "volume": "",
      "last_updated": "1735095343",
      "groups": {
        "": "/proxy/api/mangadex/chapter/e9f5026f-772a-43d5-a300-4f9386fb00ea"
      }
    },
    "34": {
      "title": "34",
      "volume": "",
      "last_updated": "1735095357",
      "groups": {
        "": "/proxy/api/mangadex/chapter/789b399e-c69e-4a29-b210-acf9588650b4"
      }
    },
    "35": {
      "title": "35",
      "volume": "",
      "last_updated": "1735095371",
      "groups": {
        "": "/proxy/api/mangadex/chapter/8d088fc9-befe-4ee0-858a-969e3e6ab917"
      }
    },
    "36": {
      "title": "36",
      "volume": "",
      "last_updated": "1735095386",
      "groups": {
        "": "/proxy/api/mangadex/chapter/2f5443ad-406e-4273-a9bf-b14dfb8da808"
      }
    },
    "37": {
      "title": "37",
      "volume": "",
      "last_updated": "1735095400",
      "groups": {
        "": "/proxy/api/mangadex/chapter/90fd4a12-c37e-4849-abcf-8ab8fe9593d8"
      }
    },
    "38": {
      "title": "38",
      "volume": "",
      "last_updated": "1735095414",
      "groups": {
        "": "/proxy/api/mangadex/chapter/aafc6dbc-5b11-4726-9042-bdf72eefbf33"
      }
    },
    "39": {
      "title": "39",
      "volume": "",
      "last_updated": "1735095428",
      "groups": {
        "": "/proxy/api/mangadex/chapter/6fa2e8ca-cef0-4df5-8561-5736e2a58dbc"
      }
    },
    "40": {
      "title": "40",
      "volume": "",
      "last_updated": "1735095573",
      "groups": {
        "": "/proxy/api/mangadex/chapter/e5e9fba3-f4e5-4b3a-be29-69f5671dc8a3"
      }
    },
    "41": {
      "title": "41",
      "volume": "",
      "last_updated": "1735095588",
      "groups": {
        "": "/proxy/api/mangadex/chapter/477d3531-79c6-4dc5-9cb0-7bd8c9ca8ed6"
      }
    },
    "42": {
      "title": "42",
      "volume": "",
      "last_updated": "1735095601",
      "groups": {
        "": "/proxy/api/mangadex/chapter/f0bb2ead-794f-4888-a3e1-c157f536a4aa"
      }
    },
    "43": {
      "title": "43",
      "volume": "",
      "last_updated": "1735095615",
      "groups": {
        "": "/proxy/api/mangadex/chapter/5e673419-4e1f-4769-a528-e5c90faa6dfa"
      }
    },
    "44": {
      "title": "44",
      "volume": "",
      "last_updated": "1735095627",
      "groups": {
        "": "/proxy/api/mangadex/chapter/4a3f6243-8d47-4e16-9bf2-d0c921bbea19"
      }
    },
    "45": {
      "title": "45",
      "volume": "",
      "last_updated": "1735095639",
      "groups": {
        "": "/proxy/api/mangadex/chapter/b44b68da-c8e8-46ae-a77b-c66c79fe59ea"
      }
    },
    "46": {
      "title": "46",
      "volume": "",
      "last_updated": "1735095652",
      "groups": {
        "": [
          "https://github.com/aoba-seragakii/manga/blob/main/Keeper%20of%20the%20Pearl/46/001.jpeg?raw=true",
          "https://github.com/aoba-seragakii/manga/blob/main/Keeper%20of%20the%20Pearl/46/002.jpeg?raw=true",
          "https://github.com/aoba-seragakii/manga/blob/main/Keeper%20of%20the%20Pearl/46/003.jpeg?raw=true",
          "https://github.com/aoba-seragakii/manga/blob/main/Keeper%20of%20the%20Pearl/46/004.jpeg?raw=true",
          "https://github.com/aoba-seragakii/manga/blob/main/Keeper%20of%20the%20Pearl/46/005.jpeg?raw=true",
          "https://github.com/aoba-seragakii/manga/blob/main/Keeper%20of%20the%20Pearl/46/006.jpeg?raw=true",
          "https://github.com/aoba-seragakii/manga/blob/main/Keeper%20of%20the%20Pearl/46/007.jpeg?raw=true",
          "https://github.com/aoba-seragakii/manga/blob/main/Keeper%20of%20the%20Pearl/46/008.jpeg?raw=true",
          "https://github.com/aoba-seragakii/manga/blob/main/Keeper%20of%20the%20Pearl/46/009.jpeg?raw=true",
          "https://github.com/aoba-seragakii/manga/blob/main/Keeper%20of%20the%20Pearl/46/010.jpeg?raw=true",
          "https://github.com/aoba-seragakii/manga/blob/main/Keeper%20of%20the%20Pearl/46/011.jpeg?raw=true",
          "https://github.com/aoba-seragakii/manga/blob/main/Keeper%20of%20the%20Pearl/46/012.jpeg?raw=true",
          "https://github.com/aoba-seragakii/manga/blob/main/Keeper%20of%20the%20Pearl/46/013.jpeg?raw=true",
          "https://github.com/aoba-seragakii/manga/blob/main/Keeper%20of%20the%20Pearl/46/014.jpeg?raw=true",
          "https://github.com/aoba-seragakii/manga/blob/main/Keeper%20of%20the%20Pearl/46/015.jpeg?raw=true",
          "https://github.com/aoba-seragakii/manga/blob/main/Keeper%20of%20the%20Pearl/46/016.jpeg?raw=true",
          "https://github.com/aoba-seragakii/manga/blob/main/Keeper%20of%20the%20Pearl/46/017.jpeg?raw=true",
          "https://github.com/aoba-seragakii/manga/blob/main/Keeper%20of%20the%20Pearl/46/018.jpeg?raw=true",
          "https://github.com/aoba-seragakii/manga/blob/main/Keeper%20of%20the%20Pearl/46/019.jpeg?raw=true",
          "https://github.com/aoba-seragakii/manga/blob/main/Keeper%20of%20the%20Pearl/46/020.jpeg?raw=true",
          "https://github.com/aoba-seragakii/manga/blob/main/Keeper%20of%20the%20Pearl/46/021.jpeg?raw=true",
          "https://github.com/aoba-seragakii/manga/blob/main/Keeper%20of%20the%20Pearl/46/022.jpeg?raw=true",
          "https://github.com/aoba-seragakii/manga/blob/main/Keeper%20of%20the%20Pearl/46/023.jpeg?raw=true",
          "https://github.com/aoba-seragakii/manga/blob/main/Keeper%20of%20the%20Pearl/46/024.jpeg?raw=true",
          "https://github.com/aoba-seragakii/manga/blob/main/Keeper%20of%20the%20Pearl/46/025.jpeg?raw=true",
          "https://github.com/aoba-seragakii/manga/blob/main/Keeper%20of%20the%20Pearl/46/026.jpeg?raw=true",
          "https://github.com/aoba-seragakii/manga/blob/main/Keeper%20of%20the%20Pearl/46/027.jpeg?raw=true",
          "https://github.com/aoba-seragakii/manga/blob/main/Keeper%20of%20the%20Pearl/46/028.jpeg?raw=true",
          "https://github.com/aoba-seragakii/manga/blob/main/Keeper%20of%20the%20Pearl/46/029.jpeg?raw=true"
        ]
      }
    },
    "47": {
      "title": "47",
      "volume": "",
      "last_updated": "1735096872",
      "groups": {
        "": [
          "https://github.com/aoba-seragakii/manga/blob/main/Keeper%20of%20the%20Pearl/47/001.jpeg?raw=true",
          "https://github.com/aoba-seragakii/manga/blob/main/Keeper%20of%20the%20Pearl/47/002.jpeg?raw=true",
          "https://github.com/aoba-seragakii/manga/blob/main/Keeper%20of%20the%20Pearl/47/003.jpeg?raw=true",
          "https://github.com/aoba-seragakii/manga/blob/main/Keeper%20of%20the%20Pearl/47/004.jpeg?raw=true",
          "https://github.com/aoba-seragakii/manga/blob/main/Keeper%20of%20the%20Pearl/47/005.jpeg?raw=true",
          "https://github.com/aoba-seragakii/manga/blob/main/Keeper%20of%20the%20Pearl/47/006.jpeg?raw=true",
          "https://github.com/aoba-seragakii/manga/blob/main/Keeper%20of%20the%20Pearl/47/007.jpeg?raw=true",
          "https://github.com/aoba-seragakii/manga/blob/main/Keeper%20of%20the%20Pearl/47/008.jpeg?raw=true",
          "https://github.com/aoba-seragakii/manga/blob/main/Keeper%20of%20the%20Pearl/47/009.jpeg?raw=true",
          "https://github.com/aoba-seragakii/manga/blob/main/Keeper%20of%20the%20Pearl/47/010.jpeg?raw=true",
          "https://github.com/aoba-seragakii/manga/blob/main/Keeper%20of%20the%20Pearl/47/011.jpeg?raw=true",
          "https://github.com/aoba-seragakii/manga/blob/main/Keeper%20of%20the%20Pearl/47/012.jpeg?raw=true",
          "https://github.com/aoba-seragakii/manga/blob/main/Keeper%20of%20the%20Pearl/47/013.jpeg?raw=true",
          "https://github.com/aoba-seragakii/manga/blob/main/Keeper%20of%20the%20Pearl/47/014.jpeg?raw=true",
          "https://github.com/aoba-seragakii/manga/blob/main/Keeper%20of%20the%20Pearl/47/015.jpeg?raw=true",
          "https://github.com/aoba-seragakii/manga/blob/main/Keeper%20of%20the%20Pearl/47/016.jpeg?raw=true",
          "https://github.com/aoba-seragakii/manga/blob/main/Keeper%20of%20the%20Pearl/47/017.jpeg?raw=true",
          "https://github.com/aoba-seragakii/manga/blob/main/Keeper%20of%20the%20Pearl/47/018.jpeg?raw=true",
          "https://github.com/aoba-seragakii/manga/blob/main/Keeper%20of%20the%20Pearl/47/019.jpeg?raw=true",
          "https://github.com/aoba-seragakii/manga/blob/main/Keeper%20of%20the%20Pearl/47/020.jpeg?raw=true",
          "https://github.com/aoba-seragakii/manga/blob/main/Keeper%20of%20the%20Pearl/47/021.jpeg?raw=true",
          "https://github.com/aoba-seragakii/manga/blob/main/Keeper%20of%20the%20Pearl/47/022.jpeg?raw=true",
          "https://github.com/aoba-seragakii/manga/blob/main/Keeper%20of%20the%20Pearl/47/023.jpeg?raw=true",
          "https://github.com/aoba-seragakii/manga/blob/main/Keeper%20of%20the%20Pearl/47/024.jpeg?raw=true"
        ]
      }
    },
    "48": {
      "title": "48",
      "volume": "",
      "last_updated": "1735096937",
      "groups": {
        "": [
          "https://github.com/aoba-seragakii/manga/blob/main/Keeper%20of%20the%20Pearl/48/001.jpeg?raw=true",
          "https://github.com/aoba-seragakii/manga/blob/main/Keeper%20of%20the%20Pearl/48/002.jpeg?raw=true",
          "https://github.com/aoba-seragakii/manga/blob/main/Keeper%20of%20the%20Pearl/48/003.jpeg?raw=true",
          "https://github.com/aoba-seragakii/manga/blob/main/Keeper%20of%20the%20Pearl/48/004.jpeg?raw=true",
          "https://github.com/aoba-seragakii/manga/blob/main/Keeper%20of%20the%20Pearl/48/005.jpeg?raw=true",
          "https://github.com/aoba-seragakii/manga/blob/main/Keeper%20of%20the%20Pearl/48/006.jpeg?raw=true",
          "https://github.com/aoba-seragakii/manga/blob/main/Keeper%20of%20the%20Pearl/48/007.jpeg?raw=true",
          "https://github.com/aoba-seragakii/manga/blob/main/Keeper%20of%20the%20Pearl/48/008.jpeg?raw=true",
          "https://github.com/aoba-seragakii/manga/blob/main/Keeper%20of%20the%20Pearl/48/009.jpeg?raw=true",
          "https://github.com/aoba-seragakii/manga/blob/main/Keeper%20of%20the%20Pearl/48/010.jpeg?raw=true",
          "https://github.com/aoba-seragakii/manga/blob/main/Keeper%20of%20the%20Pearl/48/011.jpeg?raw=true",
          "https://github.com/aoba-seragakii/manga/blob/main/Keeper%20of%20the%20Pearl/48/012.jpeg?raw=true",
          "https://github.com/aoba-seragakii/manga/blob/main/Keeper%20of%20the%20Pearl/48/013.jpeg?raw=true",
          "https://github.com/aoba-seragakii/manga/blob/main/Keeper%20of%20the%20Pearl/48/014.jpeg?raw=true",
          "https://github.com/aoba-seragakii/manga/blob/main/Keeper%20of%20the%20Pearl/48/015.jpeg?raw=true",
          "https://github.com/aoba-seragakii/manga/blob/main/Keeper%20of%20the%20Pearl/48/016.jpeg?raw=true",
          "https://github.com/aoba-seragakii/manga/blob/main/Keeper%20of%20the%20Pearl/48/017.jpeg?raw=true",
          "https://github.com/aoba-seragakii/manga/blob/main/Keeper%20of%20the%20Pearl/48/018.jpeg?raw=true",
          "https://github.com/aoba-seragakii/manga/blob/main/Keeper%20of%20the%20Pearl/48/019.jpeg?raw=true",
          "https://github.com/aoba-seragakii/manga/blob/main/Keeper%20of%20the%20Pearl/48/020.jpeg?raw=true",
          "https://github.com/aoba-seragakii/manga/blob/main/Keeper%20of%20the%20Pearl/48/021.jpeg?raw=true",
          "https://github.com/aoba-seragakii/manga/blob/main/Keeper%20of%20the%20Pearl/48/022.jpeg?raw=true",
          "https://github.com/aoba-seragakii/manga/blob/main/Keeper%20of%20the%20Pearl/48/023.jpeg?raw=true"
        ]
      }
    },
    "49": {
      "title": "49",
      "volume": "",
      "last_updated": "1735096970",
      "groups": {
        "": [
          "https://github.com/aoba-seragakii/manga/blob/main/Keeper%20of%20the%20Pearl/49/001.jpeg?raw=true",
          "https://github.com/aoba-seragakii/manga/blob/main/Keeper%20of%20the%20Pearl/49/002.jpeg?raw=true",
          "https://github.com/aoba-seragakii/manga/blob/main/Keeper%20of%20the%20Pearl/49/003.jpeg?raw=true",
          "https://github.com/aoba-seragakii/manga/blob/main/Keeper%20of%20the%20Pearl/49/004.jpeg?raw=true",
          "https://github.com/aoba-seragakii/manga/blob/main/Keeper%20of%20the%20Pearl/49/005.jpeg?raw=true",
          "https://github.com/aoba-seragakii/manga/blob/main/Keeper%20of%20the%20Pearl/49/006.jpeg?raw=true",
          "https://github.com/aoba-seragakii/manga/blob/main/Keeper%20of%20the%20Pearl/49/007.jpeg?raw=true",
          "https://github.com/aoba-seragakii/manga/blob/main/Keeper%20of%20the%20Pearl/49/008.jpeg?raw=true",
          "https://github.com/aoba-seragakii/manga/blob/main/Keeper%20of%20the%20Pearl/49/009.jpeg?raw=true",
          "https://github.com/aoba-seragakii/manga/blob/main/Keeper%20of%20the%20Pearl/49/010.jpeg?raw=true",
          "https://github.com/aoba-seragakii/manga/blob/main/Keeper%20of%20the%20Pearl/49/011.jpeg?raw=true",
          "https://github.com/aoba-seragakii/manga/blob/main/Keeper%20of%20the%20Pearl/49/012.jpeg?raw=true",
          "https://github.com/aoba-seragakii/manga/blob/main/Keeper%20of%20the%20Pearl/49/013.jpeg?raw=true",
          "https://github.com/aoba-seragakii/manga/blob/main/Keeper%20of%20the%20Pearl/49/014.jpeg?raw=true",
          "https://github.com/aoba-seragakii/manga/blob/main/Keeper%20of%20the%20Pearl/49/015.jpeg?raw=true",
          "https://github.com/aoba-seragakii/manga/blob/main/Keeper%20of%20the%20Pearl/49/016.jpeg?raw=true",
          "https://github.com/aoba-seragakii/manga/blob/main/Keeper%20of%20the%20Pearl/49/017.jpeg?raw=true",
          "https://github.com/aoba-seragakii/manga/blob/main/Keeper%20of%20the%20Pearl/49/018.jpeg?raw=true",
          "https://github.com/aoba-seragakii/manga/blob/main/Keeper%20of%20the%20Pearl/49/019.jpeg?raw=true",
          "https://github.com/aoba-seragakii/manga/blob/main/Keeper%20of%20the%20Pearl/49/020.jpeg?raw=true",
          "https://github.com/aoba-seragakii/manga/blob/main/Keeper%20of%20the%20Pearl/49/021.jpeg?raw=true",
          "https://github.com/aoba-seragakii/manga/blob/main/Keeper%20of%20the%20Pearl/49/022.jpeg?raw=true",
          "https://github.com/aoba-seragakii/manga/blob/main/Keeper%20of%20the%20Pearl/49/023.jpeg?raw=true",
          "https://github.com/aoba-seragakii/manga/blob/main/Keeper%20of%20the%20Pearl/49/024.jpeg?raw=true",
          "https://github.com/aoba-seragakii/manga/blob/main/Keeper%20of%20the%20Pearl/49/025.jpeg?raw=true",
          "https://github.com/aoba-seragakii/manga/blob/main/Keeper%20of%20the%20Pearl/49/026.jpeg?raw=true",
          "https://github.com/aoba-seragakii/manga/blob/main/Keeper%20of%20the%20Pearl/49/027.jpeg?raw=true",
          "https://github.com/aoba-seragakii/manga/blob/main/Keeper%20of%20the%20Pearl/49/028.jpeg?raw=true"
        ]
      }
    },
    "39.5": {
      "title": "39.5",
      "volume": "",
      "last_updated": "1735095557",
      "groups": {
        "": "/proxy/api/mangadex/chapter/ac615970-ae05-419f-a670-f32c79c2f8b9"
      }
    }
  }
}